fc3u-0.0.5.dist-info/licenses/AUTHORS.rst
fc3u-0.0.5.dist-info/licenses/LICENSE.txt
fractionalcover3/__init__.py
fractionalcover3/compute_fractionalcover.py
fractionalcover3/compute_seasonalfcover.py
fractionalcover3/data.py
fractionalcover3/fc_model_fit.py
fractionalcover3/qv_fractionalcover_sentinel2.py
fractionalcover3/qv_seasonalfcover_sentinel2.py
fractionalcover3/unmixcover.py
fractionalcover3/pkgdata/fcModel_256x128x256.tflite
fractionalcover3/pkgdata/fcModel_256x64x256.tflite
fractionalcover3/pkgdata/fcModel_32x32x32.tflite
fractionalcover3/pkgdata/fcModel_64x64x64.tflite
fc3u-0.0.5.dist-info/METADATA
fc3u-0.0.5.dist-info/WHEEL
fc3u-0.0.5.dist-info/entry_points.txt
fc3u-0.0.5.dist-info/top_level.txt
fc3u-0.0.5.dist-info/RECORD
