Metadata-Version: 2.4
Name: fc3u
Version: 0.0.5
Summary: Vegetation fractional cover estimates via a TensorFlow-trained MLP model
Home-page: https://gitlab.com/jrsrp/themes/cover/fractionalcover3
Author: Borevitz Labs Australian National University
Author-email: Yasar Adeel Ansari <u6737670@anu.edu.au>
Maintainer: Yasar Adeel Ansari
Maintainer-email: yasar.ansari@anu.edu.au
License: MIT
Project-URL: Documentation, https://jrsrp.gitlab.io/themes/cover/fractionalcover/
Platform: linux
Platform: macOS
Classifier: Development Status :: 4 - Beta
Classifier: Programming Language :: Python :: 3
Classifier: License :: OSI Approved :: MIT License
Requires-Python: >=3.10
License-File: LICENSE.txt
License-File: AUTHORS.rst
Requires-Dist: numpy<2
Requires-Dist: tensorflow
Provides-Extra: rsc
Requires-Dist: rsc; extra == "rsc"
Requires-Dist: coloredlogs; extra == "rsc"
Requires-Dist: click; extra == "rsc"
Provides-Extra: testing
Requires-Dist: pytest; extra == "testing"
Requires-Dist: pytest-cov; extra == "testing"
Dynamic: license-file
